__init__.py
kraken_functions.py
libraries.py
cripto_show-1.0.0.dist-info/METADATA
cripto_show-1.0.0.dist-info/WHEEL
cripto_show-1.0.0.dist-info/top_level.txt
cripto_show-1.0.0.dist-info/RECORD
